Metadata-Version: 1.1
Name: django-bosssearch
Version: 1.1
Summary: Search with Yahoo BOSS!
Home-page: https://bitbucket.org/jaap3/django-bosssearch/
Author: Jaap Roes (Eight Media)
Author-email: jaap@eight.nl
License: MIT
Platform: UNKNOWN
Classifier: Development Status :: 5 - Production/Stable
Classifier: Environment :: Web Environment
Classifier: Framework :: Django
Classifier: Intended Audience :: Developers
Classifier: License :: OSI Approved :: MIT License
Classifier: Operating System :: OS Independent
Classifier: Programming Language :: Python
